{
  "run_date": "2026-07-09",
  "fifo_summary_present": true,
  "total_realized_pnl": 126558.46413023002,
  "total_unrealized_pnl": 185250.97032099997,
  "total_dividends": 710.66,
  "total_withholding_tax": -15.7,
  "total_pil_dividends": -181792.48,
  "total_borrow_fees": -69463.82,
  "total_short_credit_interest": 15591.530000000002,
  "total_other_fees": -1.82,
  "total_bond_interest": 0.0,
  "total_pnl": 76837.80445123001,
  "excluded_cash_interest_base": -21692.761916900003,
  "borrow_mode": "borrow_fee_details_cumulative_by_symbol",
  "borrow_total_account_source": -69463.82,
  "borrow_details_file_present": true,
  "borrow_details_rows_cumulative": 384,
  "universe_source": "/home/runner/work/ls-algo/ls-algo/data/runs/2026-07-09/etf_screened_today.csv",
  "universe_allowed_etfs": 563,
  "universe_allowed_underlyings": 275,
  "kept_symbols": 576,
  "kept_underlyings": 209,
  "net_exposure_total": -34107.50240454776,
  "gross_exposure_total": 4275995.503954853,
  "net_exposure_bucket_1": -264521.5223231843,
  "gross_exposure_bucket_1": 3274619.550215563,
  "net_exposure_bucket_2": -40192.23191604222,
  "gross_exposure_bucket_2": 665507.4590627748,
  "net_exposure_bucket_3": 100499.4491482321,
  "gross_exposure_bucket_3": 101750.2119900679,
  "net_exposure_bucket_5": 33.63896066599773,
  "gross_exposure_bucket_5": 43381.55896066599,
  "net_exposure_bucket_4": 303237.3732555967,
  "gross_exposure_bucket_4": 303237.3732555967,
  "net_exposure_unbucketed": -32005.74,
  "gross_exposure_unbucketed": 32005.74,
  "net_exposure_bucket_4_pair": 279734.5936366637,
  "gross_exposure_bucket_4_pair": 647692.4308896132,
  "yfinance_override": false,
  "yfinance_symbols_overridden": 0,
  "bucket_split_method": "held_exposure",
  "bucket_component_split_method": "lot_timed",
  "b12_spot_split_method": "ledger_fifo",
  "b12_spot_exposure_method": "sleeve_balance",
  "b12_spot_pnl_method": "ledger_fifo",
  "b12_pnl_mode": "plan_b4_inject",
  "plan_b4_pnl_mode": "inject_slice",
  "plan_sleeve_bucketing": "sleeve_first",
  "b4_underlying_exposure_mode": "plan_structural",
  "b4_plan_exposure_underlyings": [
    "AMD",
    "ASTS",
    "COIN",
    "CRWV",
    "IREN",
    "LITE",
    "MSTR",
    "NBIS",
    "QBTS",
    "RGTI",
    "RKLB",
    "SNDK",
    "SPCX"
  ],
  "b4_underlying_attribution": "etf_implied",
  "b4_attribution_min_usd": 500.0,
  "b4_etf_implied_underlyings": [
    "AMD",
    "ASTS",
    "COIN",
    "IREN",
    "LITE",
    "MSTR",
    "NBIS",
    "RGTI",
    "RKLB",
    "SNDK"
  ],
  "b4_attribution_sources": {
    "plan": [
      "AMD",
      "COIN",
      "LITE",
      "MSTR",
      "NBIS",
      "QBTS",
      "RKLB",
      "SNDK",
      "SPCX"
    ],
    "etf_implied": [
      "ASTS",
      "IREN",
      "RGTI"
    ]
  },
  "bucket3_flow_low_delta_symbols": [
    "AZYY",
    "NVYY",
    "PLYY",
    "TQQY",
    "TSYY"
  ],
  "bucket3_flow_program_symbols": [
    "AMZO",
    "AZYY",
    "DUST",
    "ETHD",
    "EWV",
    "FAZ",
    "LABD",
    "NVDQ",
    "NVYY",
    "PLTZ",
    "PLYY",
    "SDS",
    "SOXS",
    "SQQQ",
    "TQQY",
    "TSLQ",
    "TSYY",
    "ZSL"
  ],
  "net_exposure_bucket_1_full": -438820.4785200888,
  "net_exposure_bucket_2_full": -58990.7071927815,
  "net_exposure_bucket_4_full": 463703.68330832245,
  "spot_ratio_max_diff": 5.551115123125783e-17,
  "spot_ratio_max_diff_pnl": 0.8620759782722498,
  "spot_ratio_gate_passed": true,
  "spot_ratio_gate_mode": "exposure_vs_plan_or_hedge_residual",
  "exposure_reconciliation_tol_gross_pct": 0.005,
  "exposure_reconciliation_tol_net_abs_usd": 10000.0,
  "bucket_state_path": "/home/runner/work/ls-algo/ls-algo/data/accounting/underlying_bucket_state.csv",
  "bucket_realized_underlyings_from_trade_timing": 248,
  "pnl_underlying_scope": "bucket_1_2_4_5",
  "bucket4_pairs": 65,
  "excluded_underlyings_exposure": [
    "APLD",
    "AXP",
    "BRK.B",
    "CBRS",
    "JPM",
    "SMR"
  ],
  "excluded_symbols_exposure": [
    "APLD",
    "APLX",
    "APLZ",
    "AXP",
    "AXPG",
    "BRK.B",
    "BRKC",
    "BRKU",
    "BRKW",
    "CBRG",
    "CBRS",
    "CBRX",
    "CBRZ",
    "JPM",
    "SMR",
    "SMU",
    "SMUP",
    "SMZ"
  ],
  "bucket_pnl": {
    "bucket_1": 56153.399109654056,
    "bucket_2": 40523.08073707818,
    "bucket_3": 3912.5578727095426,
    "bucket_5": 253.74147990108008,
    "bucket_4": -24004.974748112858
  },
  "capital_snapshot": {
    "net_capital_stock_sleeves": -800803.3042767139,
    "net_capital_bucket_3": 0.0,
    "gross_capital_stock_sleeves": 4053091.652412072,
    "gross_capital_bucket_3": 0.0,
    "margin_req_stock_sleeves": 1322637.583099302,
    "margin_req_bucket_3": 0.0,
    "net_capital_bucket_1": 359721.1958397902,
    "net_capital_bucket_2": -905684.2901165041,
    "net_capital_bucket_4": -222267.90999999997,
    "net_capital_bucket_5": -32572.3,
    "gross_capital_bucket_1": 2112075.3925285754,
    "gross_capital_bucket_2": 1686176.0498834962,
    "gross_capital_bucket_4": 222267.90999999997,
    "gross_capital_bucket_5": 32572.3,
    "margin_req_bucket_1": 837405.042194909,
    "margin_req_bucket_2": 339218.835296773,
    "margin_req_bucket_4": 132999.238516968,
    "margin_req_bucket_5": 13014.467090651999
  },
  "nav_usd": 1050000.0,
  "nav_source": "config:capital_usd"
}