{
  "run_date": "2026-05-16",
  "fifo_summary_present": true,
  "total_realized_pnl": -8754.839055070013,
  "total_unrealized_pnl": 119729.99879900001,
  "total_dividends": 664.99,
  "total_withholding_tax": -15.7,
  "total_pil_dividends": -32081.769999999997,
  "total_borrow_fees": -19081.25,
  "total_short_credit_interest": 4760.929999999999,
  "total_other_fees": -1.82,
  "total_bond_interest": 0.0,
  "total_pnl": 65220.5397439301,
  "excluded_cash_interest_base": -9846.517540700002,
  "borrow_mode": "borrow_fee_details_cumulative_by_symbol",
  "borrow_total_account_source": -19081.25,
  "borrow_details_file_present": true,
  "borrow_details_rows_cumulative": 330,
  "universe_source": "C:\\Users\\werdn\\Documents\\Investing\\ls-algo\\data\\etf_screened_today.csv",
  "universe_allowed_etfs": 492,
  "universe_allowed_underlyings": 240,
  "kept_symbols": 545,
  "kept_underlyings": 202,
  "net_exposure_total": -2218.1628455790924,
  "gross_exposure_total": 2696438.675345081,
  "net_exposure_bucket_1": -6572.033519233504,
  "gross_exposure_bucket_1": 2383702.134387427,
  "net_exposure_bucket_2": -9333.500601835778,
  "gross_exposure_bucket_2": 299049.1696821632,
  "net_exposure_bucket_3": 91812.375928978,
  "gross_exposure_bucket_3": 91812.375928978,
  "net_exposure_bucket_4": 13687.371275490175,
  "gross_exposure_bucket_4": 13687.371275490175,
  "net_exposure_unbucketed": 0.0,
  "gross_exposure_unbucketed": 0.0,
  "net_exposure_bucket_4_pair": 13687.371275490174,
  "gross_exposure_bucket_4_pair": 215096.16062401142,
  "yfinance_override": false,
  "yfinance_symbols_overridden": 0,
  "bucket_split_method": "held_exposure",
  "bucket_component_split_method": "lot_timed",
  "b12_spot_split_method": "ledger_fifo",
  "b12_spot_exposure_method": "sleeve_balance",
  "b12_pnl_mode": "lot_timed_strict",
  "plan_b4_pnl_mode": "inject_slice",
  "plan_sleeve_bucketing": "sleeve_first",
  "b4_underlying_exposure_mode": "plan_structural",
  "b4_plan_exposure_underlyings": [
    "ASTS",
    "CLSK",
    "COIN",
    "CRCL",
    "CRWV",
    "IREN",
    "MSTR",
    "NBIS",
    "QBTS",
    "RKLB"
  ],
  "b4_underlying_attribution": "etf_implied",
  "b4_attribution_min_usd": 500.0,
  "b4_partial_hedge_ratio_default": 0.75,
  "b4_etf_implied_underlyings": [
    "ASTS",
    "CLSK",
    "CRCL",
    "CRWV",
    "IREN",
    "MSTR",
    "NBIS",
    "QBTS",
    "RKLB"
  ],
  "b4_attribution_sources": {
    "plan": [
      "ASTS",
      "CLSK",
      "COIN",
      "CRWV",
      "IREN",
      "MSTR",
      "NBIS",
      "QBTS",
      "RKLB"
    ],
    "etf_implied": [
      "CRCL"
    ]
  },
  "bucket2_flow_low_delta_symbols": [
    "AZYY",
    "NVYY",
    "PLYY",
    "TQQY",
    "TSYY"
  ],
  "bucket3_flow_program_symbols": [
    "AMZO",
    "DUST",
    "ETHD",
    "EWV",
    "FAZ",
    "LABD",
    "NVDQ",
    "PLTZ",
    "SDS",
    "SOXS",
    "SQQQ",
    "TSLQ",
    "ZSL"
  ],
  "net_exposure_bucket_1_full": -88652.03284167079,
  "net_exposure_bucket_2_full": -27957.895953659136,
  "net_exposure_bucket_4_full": 114391.76594975078,
  "spot_ratio_max_diff": 1.1102230246251565e-16,
  "spot_ratio_max_diff_pnl": 1.0,
  "spot_ratio_gate_passed": true,
  "spot_ratio_gate_mode": "exposure_vs_plan_or_hedge_residual",
  "exposure_reconciliation_tol_gross_pct": 0.005,
  "exposure_reconciliation_tol_net_abs_usd": 10000.0,
  "bucket_state_path": "C:\\Users\\werdn\\Documents\\Investing\\ls-algo\\data\\accounting\\underlying_bucket_state.csv",
  "bucket_realized_underlyings_from_trade_timing": 461,
  "pnl_underlying_scope": "bucket_1_2_4",
  "bucket4_pairs": 63,
  "excluded_underlyings_exposure": [
    "APLD",
    "AXP",
    "BRK.B",
    "JPM",
    "SMR"
  ],
  "excluded_symbols_exposure": [
    "APLD",
    "APLX",
    "APLZ",
    "AXP",
    "AXPG",
    "BRK.B",
    "BRKC",
    "BRKU",
    "BRKW",
    "JPM",
    "SMR",
    "SMU",
    "SMUP",
    "SMZ"
  ],
  "bucket_pnl": {
    "bucket_1": 33313.00868532976,
    "bucket_2": 26870.650436777196,
    "bucket_3": 7772.19034256322,
    "bucket_4": -2735.309720740162
  }
}