{
  "run_date": "2026-06-24",
  "fifo_summary_present": true,
  "total_realized_pnl": 54283.61200827005,
  "total_unrealized_pnl": 187513.905548,
  "total_dividends": 653.79,
  "total_withholding_tax": -17.16,
  "total_pil_dividends": -133172.13999999998,
  "total_borrow_fees": -51920.950000000004,
  "total_short_credit_interest": 8960.189999999999,
  "total_other_fees": -1.82,
  "total_bond_interest": 0.0,
  "total_pnl": 66299.42755626995,
  "excluded_cash_interest_base": -17267.0634723,
  "borrow_mode": "borrow_fee_details_cumulative_by_symbol",
  "borrow_total_account_source": -51920.95,
  "borrow_details_file_present": true,
  "borrow_details_rows_cumulative": 371,
  "universe_source": "/home/runner/work/ls-algo/ls-algo/data/etf_screened_today.csv",
  "universe_allowed_etfs": 524,
  "universe_allowed_underlyings": 255,
  "kept_symbols": 554,
  "kept_underlyings": 200,
  "net_exposure_total": 133821.517065723,
  "gross_exposure_total": 3264348.338872391,
  "net_exposure_bucket_1": 26181.789364773344,
  "gross_exposure_bucket_1": 2291213.6975429216,
  "net_exposure_bucket_2": -26448.734465530822,
  "gross_exposure_bucket_2": 827084.64460121,
  "net_exposure_bucket_3": 103323.7260297729,
  "gross_exposure_bucket_3": 104615.30275674147,
  "net_exposure_bucket_4": 134734.25052996475,
  "gross_exposure_bucket_4": 145404.20836477482,
  "net_exposure_unbucketed": 0.0,
  "gross_exposure_unbucketed": 0.0,
  "net_exposure_bucket_4_pair": 107994.43169781475,
  "gross_exposure_bucket_4_pair": 272387.46130009927,
  "yfinance_override": false,
  "yfinance_symbols_overridden": 0,
  "bucket_split_method": "held_exposure",
  "bucket_component_split_method": "lot_timed",
  "b12_spot_split_method": "ledger_fifo",
  "b12_spot_exposure_method": "sleeve_balance",
  "b12_spot_pnl_method": "ledger_fifo",
  "b12_pnl_mode": "plan_b4_inject",
  "plan_b4_pnl_mode": "inject_slice",
  "plan_sleeve_bucketing": "sleeve_first",
  "b4_underlying_exposure_mode": "plan_structural",
  "b4_plan_exposure_underlyings": [
    "AMD",
    "ASTS",
    "BE",
    "COIN",
    "CRCL",
    "CRWV",
    "IREN",
    "LITE",
    "MSTR",
    "NBIS",
    "QBTS",
    "RGTI",
    "RKLB",
    "SNDK",
    "SVIX"
  ],
  "b4_underlying_attribution": "etf_implied",
  "b4_attribution_min_usd": 500.0,
  "b4_partial_hedge_ratio_default": 0.75,
  "b4_etf_implied_underlyings": [
    "AMD",
    "ASTS",
    "BE",
    "CRCL",
    "CRWV",
    "IREN",
    "LITE",
    "MSTR",
    "NBIS",
    "QBTS",
    "RGTI",
    "RKLB",
    "SVIX"
  ],
  "b4_attribution_sources": {
    "plan": [
      "AMD",
      "COIN",
      "CRWV",
      "IREN",
      "LITE",
      "MSTR",
      "NBIS",
      "QBTS",
      "RGTI",
      "RKLB",
      "SNDK",
      "SVIX"
    ],
    "etf_implied": [
      "ASTS",
      "BE",
      "CRCL"
    ]
  },
  "bucket3_flow_low_delta_symbols": [
    "AZYY",
    "NVYY",
    "PLYY",
    "TQQY",
    "TSYY"
  ],
  "bucket3_flow_program_symbols": [
    "AMZO",
    "AZYY",
    "DUST",
    "ETHD",
    "EWV",
    "FAZ",
    "LABD",
    "NVDQ",
    "NVYY",
    "PLTZ",
    "PLYY",
    "SDS",
    "SOXS",
    "SQQQ",
    "TQQY",
    "TSLQ",
    "TSYY",
    "ZSL"
  ],
  "net_exposure_bucket_1_full": -21615.224555675668,
  "net_exposure_bucket_2_full": -34754.204877558346,
  "net_exposure_bucket_4_full": 190190.94649895703,
  "spot_ratio_max_diff": 1.1102230246251565e-16,
  "spot_ratio_max_diff_pnl": 0.6796713698510246,
  "spot_ratio_gate_passed": true,
  "spot_ratio_gate_mode": "exposure_vs_plan_or_hedge_residual",
  "exposure_reconciliation_tol_gross_pct": 0.005,
  "exposure_reconciliation_tol_net_abs_usd": 10000.0,
  "bucket_state_path": "/home/runner/work/ls-algo/ls-algo/data/accounting/underlying_bucket_state.csv",
  "bucket_realized_underlyings_from_trade_timing": 236,
  "pnl_underlying_scope": "bucket_1_2_4",
  "bucket4_pairs": 62,
  "excluded_underlyings_exposure": [
    "APLD",
    "AXP",
    "BRK.B",
    "CBRS",
    "JPM",
    "SMR",
    "SPCX"
  ],
  "excluded_symbols_exposure": [
    "APLD",
    "APLX",
    "APLZ",
    "AXP",
    "AXPG",
    "BRK.B",
    "BRKC",
    "BRKU",
    "BRKW",
    "CBRG",
    "CBRS",
    "CBRX",
    "CBRZ",
    "JPM",
    "LOFF",
    "SMR",
    "SMU",
    "SMUP",
    "SMZ",
    "SNK",
    "SPAL",
    "SPAX",
    "SPCF",
    "SPCG",
    "SPCH",
    "SPCL",
    "SPCM",
    "SPCU",
    "SPCX",
    "SSPC"
  ],
  "bucket_pnl": {
    "bucket_2": 37522.90656469517,
    "bucket_1": 24265.072450021587,
    "bucket_3": 3461.9726674692,
    "bucket_4": 1049.4758740840555
  },
  "capital_snapshot": {
    "net_capital_stock_sleeves": -709402.8806166083,
    "net_capital_bucket_3": 0.0,
    "gross_capital_stock_sleeves": 3636167.922223264,
    "gross_capital_bucket_3": 0.0,
    "margin_req_stock_sleeves": 1091539.3120351085,
    "margin_req_bucket_3": 0.0,
    "net_capital_bucket_1": 393555.292010224,
    "net_capital_bucket_2": -1002909.5926268322,
    "net_capital_bucket_4": -100048.58000000002,
    "gross_capital_bucket_1": 1533119.014850096,
    "gross_capital_bucket_2": 2003000.3273731677,
    "gross_capital_bucket_4": 100048.58000000002,
    "margin_req_bucket_1": 588565.2493935523,
    "margin_req_bucket_2": 437179.553378741,
    "margin_req_bucket_4": 65794.509262815
  }
}